torchmeta/__init__.py
torchmeta/version.py
torchmeta/datasets/__init__.py
torchmeta/datasets/bach.py
torchmeta/datasets/cub.py
torchmeta/datasets/doublemnist.py
torchmeta/datasets/helpers.py
torchmeta/datasets/helpers_tabular.py
torchmeta/datasets/letter.py
torchmeta/datasets/miniimagenet.py
torchmeta/datasets/omniglot.py
torchmeta/datasets/one_hundred_plants_margin.py
torchmeta/datasets/one_hundred_plants_shape.py
torchmeta/datasets/one_hundred_plants_texture.py
torchmeta/datasets/pascal5i.py
torchmeta/datasets/tcga.py
torchmeta/datasets/tieredimagenet.py
torchmeta/datasets/triplemnist.py
torchmeta/datasets/utils.py
torchmeta/datasets/assets/bach/test.json
torchmeta/datasets/assets/bach/train.json
torchmeta/datasets/assets/bach/val.json
torchmeta/datasets/assets/cifar100/cifar-fs/test.json
torchmeta/datasets/assets/cifar100/cifar-fs/train.json
torchmeta/datasets/assets/cifar100/cifar-fs/val.json
torchmeta/datasets/assets/cifar100/fc100/test.json
torchmeta/datasets/assets/cifar100/fc100/train.json
torchmeta/datasets/assets/cifar100/fc100/val.json
torchmeta/datasets/assets/cub/test.json
torchmeta/datasets/assets/cub/train.json
torchmeta/datasets/assets/cub/val.json
torchmeta/datasets/assets/doublemnist/test.json
torchmeta/datasets/assets/doublemnist/train.json
torchmeta/datasets/assets/doublemnist/val.json
torchmeta/datasets/assets/letter/test.json
torchmeta/datasets/assets/letter/train.json
torchmeta/datasets/assets/letter/val.json
torchmeta/datasets/assets/omniglot/test.json
torchmeta/datasets/assets/omniglot/train.json
torchmeta/datasets/assets/omniglot/val.json
torchmeta/datasets/assets/one_hundred_plants_margin/test.json
torchmeta/datasets/assets/one_hundred_plants_margin/train.json
torchmeta/datasets/assets/one_hundred_plants_margin/val.json
torchmeta/datasets/assets/one_hundred_plants_shape/test.json
torchmeta/datasets/assets/one_hundred_plants_shape/train.json
torchmeta/datasets/assets/one_hundred_plants_shape/val.json
torchmeta-1.8.0.dist-info/LICENSE
torchmeta-1.8.0.dist-info/METADATA
torchmeta-1.8.0.dist-info/WHEEL
torchmeta-1.8.0.dist-info/top_level.txt
torchmeta-1.8.0.dist-info/RECORD
