Metadata-Version: 2.1
Name: torchmeta
Version: 1.8.0
Summary: Dataloaders for meta-learning in Pytorch
Home-page: https://github.com/tristandeleu/pytorch-meta
Author: Tristan Deleu
Author-email: tristan.deleu@gmail.com
License: MIT
Keywords: meta-learning,pytorch,few-shot,few-shot learning
Platform: UNKNOWN
Classifier: Development Status :: 5 - Production/Stable
Classifier: Topic :: Scientific/Engineering :: Artificial Intelligence
Classifier: Intended Audience :: Science/Research
Classifier: Programming Language :: Python :: 3
Classifier: Programming Language :: Python :: 3.6
Classifier: Programming Language :: Python :: 3.7
Classifier: Programming Language :: Python :: 3.8
Classifier: License :: OSI Approved :: MIT License
License-File: LICENSE
Requires-Dist: torch (<1.10.0,>=1.4.0)
Requires-Dist: torchvision (<0.11.0,>=0.5.0)
Requires-Dist: numpy (>=1.14.0)
Requires-Dist: Pillow (>=7.0.0)
Requires-Dist: h5py
Requires-Dist: tqdm (>=4.0.0)
Requires-Dist: requests
Requires-Dist: ordered-set
Provides-Extra: tcga
Requires-Dist: pandas (~=0.24.0) ; extra == 'tcga'
Requires-Dist: academictorrents (~=2.1.0) ; extra == 'tcga'
Requires-Dist: six (~=1.11.0) ; extra == 'tcga'
Provides-Extra: test
Requires-Dist: flaky ; extra == 'test'
